delimited_protobuf.py
delimited_protobuf-1.0.0.dist-info/LICENSE
delimited_protobuf-1.0.0.dist-info/METADATA
delimited_protobuf-1.0.0.dist-info/WHEEL
delimited_protobuf-1.0.0.dist-info/top_level.txt
delimited_protobuf-1.0.0.dist-info/RECORD
