Metadata-Version: 2.1
Name: delimited-protobuf
Version: 1.0.0
Summary: A read/write library for length-delimited protobuf message
Home-page: https://github.com/soulmachine/delimited-protobuf
Author: soulmachine
License: Apache License 2.0
Keywords: protobuf,delimited,serialization
Platform: UNKNOWN
Classifier: License :: OSI Approved :: Apache Software License
Classifier: Topic :: Software Development :: Libraries :: Python Modules
Requires-Dist: protobuf
